ezkernel/__init__.py
ezkernel/__main__.py
ezkernel/cli.py
ezkernel/kernel_manager.py
ezkernel-0.1.0.dist-info/LICENSE
ezkernel-0.1.0.dist-info/METADATA
ezkernel-0.1.0.dist-info/WHEEL
ezkernel-0.1.0.dist-info/entry_points.txt
ezkernel-0.1.0.dist-info/RECORD
