Metadata-Version: 2.1
Name: ezkernel
Version: 0.1.0
Summary: A simple CLI wrapper to manage Jupyter kernels
License: MIT
Author: Ali Tavallaie
Author-email: a.tavallaie@gmail.com
Requires-Python: >=3.10,<4.0
Classifier: License :: OSI Approved :: MIT License
Classifier: Programming Language :: Python :: 3
Classifier: Programming Language :: Python :: 3.10
Classifier: Programming Language :: Python :: 3.11
Classifier: Programming Language :: Python :: 3.12
Requires-Dist: ipykernel (>=6.29.3,<7.0.0)
Requires-Dist: jupyter-core (>=5.7.1,<6.0.0)
Requires-Dist: typer[all] (>=0.9.0,<0.10.0)
Project-URL: Documentation, https://github.com/tavallaie/ezkernel
Project-URL: Homepage, https://github.com/tavallaie/ezkernel
Project-URL: Repository, https://github.com/tavallaie/ezkernel
